.DS_Store
vulcan_athena/__init__.py
vulcan_athena/price_analysis.py
vulcan_athena/time_series.py
vulcan_athena/vulcan_athena.py
vulcan_athena/mirandareporting/__init__.py
vulcan_athena/mirandareporting/data_wrangler.py
vulcan_athena/mirandareporting/execution_file_new.py
vulcan_athena/mirandareporting/fifo_business_logic.py
vulcan_athena/mirandareporting/generic_units_logic.py
vulcan_athena/mirandareporting/inventory_on_hand_engine.py
vulcan_athena/mirandareporting/reporting_framework.py
vulcan_athena/mirandareporting/setup.py
vulcan_athena/mirandareporting/ssp_logic.py
vulcan_athena/weather_reporting/__init__.py
vulcan_athena/weather_reporting/setup.py
vulcan_athena/weather_reporting/weather_api.py
vulcan_athena-0.2.6.dist-info/AUTHORS.rst
vulcan_athena-0.2.6.dist-info/LICENSE
vulcan_athena-0.2.6.dist-info/METADATA
vulcan_athena-0.2.6.dist-info/WHEEL
vulcan_athena-0.2.6.dist-info/top_level.txt
vulcan_athena-0.2.6.dist-info/RECORD
