Metadata-Version: 2.1
Name: vulcan-athena
Version: 0.2.6
Summary: Python packaging for Athena's reporting framework
Home-page: https://github.com/mehulnagpurkar/vulcan_athena
Author: Mehul Nagpurkar
Author-email: mehul.nagpurkar@pitcher.com.au
License: MIT license
Keywords: vulcan_athena
Platform: UNKNOWN
Classifier: Development Status :: 2 - Pre-Alpha
Classifier: Intended Audience :: Developers
Classifier: License :: OSI Approved :: MIT License
Classifier: Natural Language :: English
Classifier: Programming Language :: Python :: 3
Classifier: Programming Language :: Python :: 3.5
Classifier: Programming Language :: Python :: 3.6
Classifier: Programming Language :: Python :: 3.7
Classifier: Programming Language :: Python :: 3.8
Requires-Python: >=3.5
Requires-Dist: pandas
Requires-Dist: numpy
Requires-Dist: scipy
Requires-Dist: seaborn
Requires-Dist: matplotlib
